bbrc_pyxnat-1.6.4.data/scripts/sessionmirror.py
bbrc_pyxnat-1.6.4.dist-info/licenses/LICENSE
pyxnat/__init__.py
pyxnat/version.py
pyxnat/core/__init__.py
pyxnat/core/array.py
pyxnat/core/attributes.py
pyxnat/core/downloadutils.py
pyxnat/core/errors.py
pyxnat/core/help.py
pyxnat/core/httputil.py
pyxnat/core/interfaces.py
pyxnat/core/jsonutil.py
pyxnat/core/manage.py
pyxnat/core/pathutil.py
pyxnat/core/pipelines.py
pyxnat/core/provenance.py
pyxnat/core/resources.py
pyxnat/core/schema.py
pyxnat/core/search.py
pyxnat/core/select.py
pyxnat/core/tags.py
pyxnat/core/uriutil.py
pyxnat/core/users.py
pyxnat/core/xpass.py
pyxnat/core/xpath_store.py
pyxnat/core/derivatives/3dasl.py
pyxnat/core/derivatives/__init__.py
pyxnat/core/derivatives/alps.py
pyxnat/core/derivatives/ashs.py
pyxnat/core/derivatives/bamos.py
pyxnat/core/derivatives/bamos_arterial.py
pyxnat/core/derivatives/basil.py
pyxnat/core/derivatives/cat12.py
pyxnat/core/derivatives/centaurz.py
pyxnat/core/derivatives/dicom.py
pyxnat/core/derivatives/donsurf.py
pyxnat/core/derivatives/dtifit.py
pyxnat/core/derivatives/freesurfer.py
pyxnat/core/derivatives/freesurfer7_extras.py
pyxnat/core/derivatives/mrtrix3.py
pyxnat/core/derivatives/pet_fdg.py
pyxnat/core/derivatives/pet_ftm.py
pyxnat/core/derivatives/qsxmt.py
pyxnat/core/derivatives/spm12.py
pyxnat/core/derivatives/validator.py
pyxnat/core/derivatives/xcp_d.py
pyxnat/tests/__init__.py
pyxnat/tests/array_test.py
pyxnat/tests/attributes_test.py
pyxnat/tests/custom_variables_test.py
pyxnat/tests/downloadutils_test.py
pyxnat/tests/experiments_test.py
pyxnat/tests/graphdata_test.py
pyxnat/tests/inspector_test.py
pyxnat/tests/interfaces_test.py
pyxnat/tests/jsonutil_test.py
pyxnat/tests/manage_test.py
pyxnat/tests/pathutil_test.py
pyxnat/tests/pipelines_test.py
pyxnat/tests/prearchive_test.py
pyxnat/tests/project_manager_test.py
pyxnat/tests/provenance_test.py
pyxnat/tests/repr_test.py
pyxnat/tests/resources_test.py
pyxnat/tests/scans_test.py
pyxnat/tests/search_test.py
pyxnat/tests/select_test.py
bbrc_pyxnat-1.6.4.dist-info/METADATA
bbrc_pyxnat-1.6.4.dist-info/WHEEL
bbrc_pyxnat-1.6.4.dist-info/top_level.txt
bbrc_pyxnat-1.6.4.dist-info/RECORD
