Metadata-Version: 2.4
Name: bbrc-pyxnat
Version: 1.6.4
Summary: XNAT in Python
Home-page: https://github.com/pyxnat/pyxnat
Author: Yannick Schwartz
Author-email: yannick.schwartz@cea.fr
License: BSD
Platform: any
Classifier: Development Status :: 4 - Beta
Classifier: Environment :: Console
Classifier: Intended Audience :: Developers
Classifier: Intended Audience :: Science/Research
Classifier: Intended Audience :: Education
Classifier: License :: OSI Approved :: BSD License
Classifier: Operating System :: OS Independent
Classifier: Topic :: Scientific/Engineering
Classifier: Topic :: Utilities
Classifier: Topic :: Internet :: WWW/HTTP
Classifier: Programming Language :: Python :: 3.9
Classifier: Programming Language :: Python :: 3.10
License-File: LICENSE
Requires-Dist: lxml>=4.3
Requires-Dist: requests>=2.20
Requires-Dist: pathlib>=1.0
Requires-Dist: pandas>=0.24
Requires-Dist: pymupdf>=1.18
Requires-Dist: pydicom
Requires-Dist: nibabel>=3.1
Dynamic: author
Dynamic: author-email
Dynamic: classifier
Dynamic: description
Dynamic: description-content-type
Dynamic: home-page
Dynamic: license
Dynamic: license-file
Dynamic: platform
Dynamic: requires-dist
Dynamic: summary
